{"223152":{"username":"shabnam@loagency.de","password":"111","password2":"111","tasks":[{"task":"excercise","date":"2022-06-27"},{"task":"shopping","date":"2022-05-28"},{"task":"studing","date":"2022-05-25"},{"task":"cooking","date":"2022-05-27"},{"task":"class math","date":"2022-05-25"},{"task":"add item","date":"2022-05-23"},{"task":"qqqqq","date":"2022-05-25"},{"task":"camping","date":"2022-05-30"},{"task":"eating","date":"2022-06-07"},{"task":"travel","date":"2022-05-31","taskId":9},{"task":"sightseeing","date":"2022-05-29","taskId":10,"status":false},{"task":"ghhh","date":"","taskId":11,"status":false},{"task":"yyuuuu","date":"","taskId":12,"status":false},{"task":"sddfgg","date":"","taskId":13,"status":false},{"task":"iiiiiiiii","date":"","taskId":14,"status":false},{"task":"wwwww","date":"","taskId":15,"status":false},{"task":"ghhh","date":"","taskId":16,"status":false},{"task":"kjjj","date":"","taskId":17,"status":false},{"task":"kkkk","date":"","taskId":18,"status":false},{"task":"eating","date":"","taskId":19,"status":false}]},"582039":{"username":"mary@loagency.de","password":"12mahSA","password2":"12mahSA","tasks":[{"task":"shopping","date":"2022-05-23"},{"task":"cooking","date":"2022-05-27"},{"task":"reading","date":"2022-05-28"}]},"655736":{"username":"samira@loagency.de","password":"52208","password2":"52208","tasks":[{"task":"shopping","date":"2022-05-27"},{"task":"studing","date":"2022-05-28"},{"task":"sport","date":"2022-05-31"},{"task":"cooking","date":"2022-05-31"}]},"862169":{"username":"aien@loagency.de","password":"33Aien","password2":"33Aien","tasks":[{"task":"project","date":"2022-05-27","userId":""},{"task":"classs","date":"2022-05-28","userId":""},{"task":"meeting","date":"2022-05-29","userId":""}]}}